TF_Binary_Classification/test.py
TF_Binary_Classification/train.py
TF_Binary_Classification-1.0.1.dist-info/METADATA
TF_Binary_Classification-1.0.1.dist-info/RECORD
TF_Binary_Classification-1.0.1.dist-info/WHEEL
TF_Binary_Classification-1.0.1.dist-info/entry_points.txt
TF_Binary_Classification-1.0.1.dist-info/top_level.txt
