Metadata-Version: 2.1
Name: TF-Binary-Classification
Version: 1.0.1
Summary: A Python package to get train and test a model for binary classification.
Home-page: https://github.com/santos97/TF-Binary-Classification
Author: Santosh Shet
Author-email: santo.shet@gmail.com
License: MIT
Platform: UNKNOWN
Classifier: License :: OSI Approved :: MIT License
Classifier: Programming Language :: Python :: 3.6
Requires-Dist: tqdm
Requires-Dist: tensorflow
Requires-Dist: mathplotlib
Requires-Dist: numpy
Requires-Dist: cv2
